CPpackage/__init__.py
CPpackage/core/__init__.py
CPpackage/db/__init__.py
CPpackage/db/config.py
CPpackage/db/sql_model.py
CPpackage/utils/__init__.py
cppackage-0.1.0.dist-info/LICENSE
cppackage-0.1.0.dist-info/METADATA
cppackage-0.1.0.dist-info/WHEEL
cppackage-0.1.0.dist-info/entry_points.txt
cppackage-0.1.0.dist-info/top_level.txt
cppackage-0.1.0.dist-info/RECORD
