Metadata-Version: 2.1
Name: cppackage
Version: 0.1.0
Summary: 超品集团自用的Python包
Home-page: https://github.com/example/CPpackage
Author: team-数智组
Author-email: m110135@163.com
Classifier: Development Status :: 3 - Alpha
Classifier: Intended Audience :: Developers
Classifier: License :: OSI Approved :: MIT License
Classifier: Programming Language :: Python :: 3
Classifier: Programming Language :: Python :: 3.8
Classifier: Programming Language :: Python :: 3.9
Classifier: Programming Language :: Python :: 3.10
Classifier: Programming Language :: Python :: 3.11
Classifier: Programming Language :: Python :: 3.12
Requires-Python: >=3.8
License-File: LICENSE
Requires-Dist: pymysql
Requires-Dist: pandas
Requires-Dist: numpy
